odoo/addons/account_consolidation/README.rst
odoo/addons/account_consolidation/__init__.py
odoo/addons/account_consolidation/__manifest__.py
odoo/addons/account_consolidation/demo/company_a_demo.xml
odoo/addons/account_consolidation/demo/company_b_demo.xml
odoo/addons/account_consolidation/demo/company_demo.xml
odoo/addons/account_consolidation/demo/consolidation_demo.xml
odoo/addons/account_consolidation/demo/currency_demo.xml
odoo/addons/account_consolidation/models/__init__.py
odoo/addons/account_consolidation/models/account.py
odoo/addons/account_consolidation/models/account_move.py
odoo/addons/account_consolidation/models/company.py
odoo/addons/account_consolidation/models/consolidation_profile.py
odoo/addons/account_consolidation/models/res_config_settings.py
odoo/addons/account_consolidation/security/account_consolidation_security.xml
odoo/addons/account_consolidation/security/account_consolidation_security.yml
odoo/addons/account_consolidation/security/ir.model.access.csv
odoo/addons/account_consolidation/security/res_groups.xml
odoo/addons/account_consolidation/tests/__init__.py
odoo/addons/account_consolidation/tests/test_account_company_rules.py
odoo/addons/account_consolidation/tests/test_account_consolidation.py
odoo/addons/account_consolidation/views/account_move_line_view.xml
odoo/addons/account_consolidation/views/account_view.xml
odoo/addons/account_consolidation/views/company_consolidation_profile.xml
odoo/addons/account_consolidation/views/consolidation_menu.xml
odoo/addons/account_consolidation/views/res_config_settings.xml
odoo/addons/account_consolidation/wizard/__init__.py
odoo/addons/account_consolidation/wizard/consolidation_base.py
odoo/addons/account_consolidation/wizard/consolidation_check.py
odoo/addons/account_consolidation/wizard/consolidation_check_view.xml
odoo/addons/account_consolidation/wizard/consolidation_consolidate.py
odoo/addons/account_consolidation/wizard/consolidation_consolidate_view.xml
odoo11_addon_account_consolidation-11.0.1.0.0.dist-info/DESCRIPTION.rst
odoo11_addon_account_consolidation-11.0.1.0.0.dist-info/METADATA
odoo11_addon_account_consolidation-11.0.1.0.0.dist-info/RECORD
odoo11_addon_account_consolidation-11.0.1.0.0.dist-info/WHEEL
odoo11_addon_account_consolidation-11.0.1.0.0.dist-info/metadata.json
odoo11_addon_account_consolidation-11.0.1.0.0.dist-info/top_level.txt
